{"metadata": {"image_height": {"datatype": "<class 'int'>", "value": [490]}, "image_width": {"datatype": "<class 'int'>", "value": [650]}, "run_date": {"datatype": "<class 'str'>", "value": ["2025-03-25T16:23:44.989372Z"]}, "plantcv_version": {"datatype": "<class 'str'>", "value": ["0.0.0"]}}, "observations": {"plant_1": {"in_bounds": {"trait": "whether the plant goes out of bounds ", "method": "plantcv.plantcv.within_frame", "scale": "none", "datatype": "<class 'bool'>", "value": true, "label": "none"}, "area": {"trait": "area", "method": "plantcv.plantcv.analyze.size", "scale": "pixels", "datatype": "<class 'int'>", "value": 379.0, "label": "pixels"}, "convex_hull_area": {"trait": "convex hull area", "method": "plantcv.plantcv.analyze.size", "scale": "pixels", "datatype": "<class 'int'>", "value": 381.0, "label": "pixels"}, "solidity": {"trait": "solidity", "method": "plantcv.plantcv.analyze.size", "scale": "none", "datatype": "<class 'float'>", "value": 0.994750656167979, "label": "none"}, "perimeter": {"trait": "perimeter", "method": "plantcv.plantcv.analyze.size", "scale": "pixels", "datatype": "<class 'int'>", "value": 77.69848430156708, "label": "pixels"}, "width": {"trait": "width", "method": "plantcv.plantcv.analyze.size", "scale": "pixels", "datatype": "<class 'int'>", "value": 26, "label": "pixels"}, "height": {"trait": "height", "method": "plantcv.plantcv.analyze.size", "scale": "pixels", "datatype": "<class 'int'>", "value": 20, "label": "pixels"}, "longest_path": {"trait": "longest path", "method": "plantcv.plantcv.analyze.size", "scale": "pixels", "datatype": "<class 'int'>", "value": 174, "label": "pixels"}, "center_of_mass": {"trait": "center of mass", "method": "plantcv.plantcv.analyze.size", "scale": "none", "datatype": "<class 'tuple'>", "value": [140.467018469657, 71.311345646438], "label": ["x", "y"]}, "convex_hull_vertices": {"trait": "convex hull vertices", "method": "plantcv.plantcv.analyze.size", "scale": "none", "datatype": "<class 'int'>", "value": 13, "label": "none"}, "object_in_frame": {"trait": "object in frame", "method": "plantcv.plantcv.analyze.size", "scale": "none", "datatype": "<class 'bool'>", "value": true, "label": "none"}, "ellipse_center": {"trait": "ellipse center", "method": "plantcv.plantcv.analyze.size", "scale": "none", "datatype": "<class 'tuple'>", "value": [140.51409912109375, 71.38440704345703], "label": ["x", "y"]}, "ellipse_major_axis": {"trait": "ellipse major axis length", "method": "plantcv.plantcv.analyze.size", "scale": "pixels", "datatype": "<class 'int'>", "value": 27.500778198242188, "label": "pixels"}, "ellipse_minor_axis": {"trait": "ellipse minor axis length", "method": "plantcv.plantcv.analyze.size", "scale": "pixels", "datatype": "<class 'int'>", "value": 16.968515396118164, "label": "pixels"}, "ellipse_angle": {"trait": "ellipse major axis angle", "method": "plantcv.plantcv.analyze.size", "scale": "degrees", "datatype": "<class 'float'>", "value": 82.25006103515625, "label": "degrees"}, "ellipse_eccentricity": {"trait": "ellipse eccentricity", "method": "plantcv.plantcv.analyze.size", "scale": "none", "datatype": "<class 'float'>", "value": 0.7869478904426657, "label": "none"}}, "plant_2": {"in_bounds": {"trait": "whether the plant goes out of bounds ", "method": "plantcv.plantcv.within_frame", "scale": "none", "datatype": "<class 'bool'>", "value": true, "label": "none"}, "area": {"trait": "area", "method": "plantcv.plantcv.analyze.size", "scale": "pixels", "datatype": "<class 'int'>", "value": 58.0, "label": "pixels"}, "convex_hull_area": {"trait": "convex hull area", "method": "plantcv.plantcv.analyze.size", "scale": "pixels", "datatype": "<class 'int'>", "value": 326.0, "label": "pixels"}, "solidity": {"trait": "solidity", "method": "plantcv.plantcv.analyze.size", "scale": "none", "datatype": "<class 'float'>", "value": 0.17791411042944785, "label": "none"}, "perimeter": {"trait": "perimeter", "method": "plantcv.plantcv.analyze.size", "scale": "pixels", "datatype": "<class 'int'>", "value": 74.81118214130402, "label": "pixels"}, "width": {"trait": "width", "method": "plantcv.plantcv.analyze.size", "scale": "pixels", "datatype": "<class 'int'>", "value": 26, "label": "pixels"}, "height": {"trait": "height", "method": "plantcv.plantcv.analyze.size", "scale": "pixels", "datatype": "<class 'int'>", "value": 26, "label": "pixels"}, "longest_path": {"trait": "longest path", "method": "plantcv.plantcv.analyze.size", "scale": "pixels", "datatype": "<class 'int'>", "value": 155, "label": "pixels"}, "center_of_mass": {"trait": "center of mass", "method": "plantcv.plantcv.analyze.size", "scale": "none", "datatype": "<class 'tuple'>", "value": [218.06896551724137, 143.86206896551724], "label": ["x", "y"]}, "convex_hull_vertices": {"trait": "convex hull vertices", "method": "plantcv.plantcv.analyze.size", "scale": "none", "datatype": "<class 'int'>", "value": 9, "label": "none"}, "object_in_frame": {"trait": "object in frame", "method": "plantcv.plantcv.analyze.size", "scale": "none", "datatype": "<class 'bool'>", "value": true, "label": "none"}, "ellipse_center": {"trait": "ellipse center", "method": "plantcv.plantcv.analyze.size", "scale": "none", "datatype": "<class 'tuple'>", "value": [218.00160217285156, 143.8172607421875], "label": ["x", "y"]}, "ellipse_major_axis": {"trait": "ellipse major axis length", "method": "plantcv.plantcv.analyze.size", "scale": "pixels", "datatype": "<class 'int'>", "value": 21.900653839111328, "label": "pixels"}, "ellipse_minor_axis": {"trait": "ellipse minor axis length", "method": "plantcv.plantcv.analyze.size", "scale": "pixels", "datatype": "<class 'int'>", "value": 19.653709411621094, "label": "pixels"}, "ellipse_angle": {"trait": "ellipse major axis angle", "method": "plantcv.plantcv.analyze.size", "scale": "degrees", "datatype": "<class 'float'>", "value": 46.65338897705078, "label": "degrees"}, "ellipse_eccentricity": {"trait": "ellipse eccentricity", "method": "plantcv.plantcv.analyze.size", "scale": "none", "datatype": "<class 'float'>", "value": 0.4412120863951132, "label": "none"}}, "plant_3": {"in_bounds": {"trait": "whether the plant goes out of bounds ", "method": "plantcv.plantcv.within_frame", "scale": "none", "datatype": "<class 'bool'>", "value": true, "label": "none"}, "area": {"trait": "area", "method": "plantcv.plantcv.analyze.size", "scale": "pixels", "datatype": "<class 'int'>", "value": 1350.0, "label": "pixels"}, "convex_hull_area": {"trait": "convex hull area", "method": "plantcv.plantcv.analyze.size", "scale": "pixels", "datatype": "<class 'int'>", "value": 5185.5, "label": "pixels"}, "solidity": {"trait": "solidity", "method": "plantcv.plantcv.analyze.size", "scale": "none", "datatype": "<class 'float'>", "value": 0.26034133641886026, "label": "none"}, "perimeter": {"trait": "perimeter", "method": "plantcv.plantcv.analyze.size", "scale": "pixels", "datatype": "<class 'int'>", "value": 541.5194400548935, "label": "pixels"}, "width": {"trait": "width", "method": "plantcv.plantcv.analyze.size", "scale": "pixels", "datatype": "<class 'int'>", "value": 110, "label": "pixels"}, "height": {"trait": "height", "method": "plantcv.plantcv.analyze.size", "scale": "pixels", "datatype": "<class 'int'>", "value": 128, "label": "pixels"}, "longest_path": {"trait": "longest path", "method": "plantcv.plantcv.analyze.size", "scale": "pixels", "datatype": "<class 'int'>", "value": 118, "label": "pixels"}, "center_of_mass": {"trait": "center of mass", "method": "plantcv.plantcv.analyze.size", "scale": "none", "datatype": "<class 'tuple'>", "value": [447.8059259259259, 53.745925925925924], "label": ["x", "y"]}, "convex_hull_vertices": {"trait": "convex hull vertices", "method": "plantcv.plantcv.analyze.size", "scale": "none", "datatype": "<class 'int'>", "value": 15, "label": "none"}, "object_in_frame": {"trait": "object in frame", "method": "plantcv.plantcv.analyze.size", "scale": "none", "datatype": "<class 'bool'>", "value": true, "label": "none"}, "ellipse_center": {"trait": "ellipse center", "method": "plantcv.plantcv.analyze.size", "scale": "none", "datatype": "<class 'tuple'>", "value": [416.70538330078125, 86.43751525878906], "label": ["x", "y"]}, "ellipse_major_axis": {"trait": "ellipse major axis length", "method": "plantcv.plantcv.analyze.size", "scale": "pixels", "datatype": "<class 'int'>", "value": 128.59677124023438, "label": "pixels"}, "ellipse_minor_axis": {"trait": "ellipse minor axis length", "method": "plantcv.plantcv.analyze.size", "scale": "pixels", "datatype": "<class 'int'>", "value": 74.51097106933594, "label": "pixels"}, "ellipse_angle": {"trait": "ellipse major axis angle", "method": "plantcv.plantcv.analyze.size", "scale": "degrees", "datatype": "<class 'float'>", "value": 39.014015197753906, "label": "degrees"}, "ellipse_eccentricity": {"trait": "ellipse eccentricity", "method": "plantcv.plantcv.analyze.size", "scale": "none", "datatype": "<class 'float'>", "value": 0.8150322700343934, "label": "none"}}, "plant_4": {"in_bounds": {"trait": "whether the plant goes out of bounds ", "method": "plantcv.plantcv.within_frame", "scale": "none", "datatype": "<class 'bool'>", "value": true, "label": "none"}, "area": {"trait": "area", "method": "plantcv.plantcv.analyze.size", "scale": "pixels", "datatype": "<class 'int'>", "value": 0, "label": "pixels"}, "convex_hull_area": {"trait": "convex hull area", "method": "plantcv.plantcv.analyze.size", "scale": "pixels", "datatype": "<class 'int'>", "value": 0, "label": "pixels"}, "solidity": {"trait": "solidity", "method": "plantcv.plantcv.analyze.size", "scale": "none", "datatype": "<class 'float'>", "value": 0, "label": "none"}, "perimeter": {"trait": "perimeter", "method": "plantcv.plantcv.analyze.size", "scale": "pixels", "datatype": "<class 'int'>", "value": 0, "label": "pixels"}, "width": {"trait": "width", "method": "plantcv.plantcv.analyze.size", "scale": "pixels", "datatype": "<class 'int'>", "value": 0, "label": "pixels"}, "height": {"trait": "height", "method": "plantcv.plantcv.analyze.size", "scale": "pixels", "datatype": "<class 'int'>", "value": 0, "label": "pixels"}, "longest_path": {"trait": "longest path", "method": "plantcv.plantcv.analyze.size", "scale": "pixels", "datatype": "<class 'int'>", "value": 0, "label": "pixels"}, "center_of_mass": {"trait": "center of mass", "method": "plantcv.plantcv.analyze.size", "scale": "none", "datatype": "<class 'tuple'>", "value": [0, 0], "label": ["x", "y"]}, "convex_hull_vertices": {"trait": "convex hull vertices", "method": "plantcv.plantcv.analyze.size", "scale": "none", "datatype": "<class 'int'>", "value": 0, "label": "none"}, "object_in_frame": {"trait": "object in frame", "method": "plantcv.plantcv.analyze.size", "scale": "none", "datatype": "<class 'bool'>", "value": true, "label": "none"}, "ellipse_center": {"trait": "ellipse center", "method": "plantcv.plantcv.analyze.size", "scale": "none", "datatype": "<class 'tuple'>", "value": [0, 0], "label": ["x", "y"]}, "ellipse_major_axis": {"trait": "ellipse major axis length", "method": "plantcv.plantcv.analyze.size", "scale": "pixels", "datatype": "<class 'int'>", "value": 0, "label": "pixels"}, "ellipse_minor_axis": {"trait": "ellipse minor axis length", "method": "plantcv.plantcv.analyze.size", "scale": "pixels", "datatype": "<class 'int'>", "value": 0, "label": "pixels"}, "ellipse_angle": {"trait": "ellipse major axis angle", "method": "plantcv.plantcv.analyze.size", "scale": "degrees", "datatype": "<class 'float'>", "value": 0.0, "label": "degrees"}, "ellipse_eccentricity": {"trait": "ellipse eccentricity", "method": "plantcv.plantcv.analyze.size", "scale": "none", "datatype": "<class 'float'>", "value": 0.0, "label": "none"}}, "plant_5": {"in_bounds": {"trait": "whether the plant goes out of bounds ", "method": "plantcv.plantcv.within_frame", "scale": "none", "datatype": "<class 'bool'>", "value": true, "label": "none"}, "area": {"trait": "area", "method": "plantcv.plantcv.analyze.size", "scale": "pixels", "datatype": "<class 'int'>", "value": 0, "label": "pixels"}, "convex_hull_area": {"trait": "convex hull area", "method": "plantcv.plantcv.analyze.size", "scale": "pixels", "datatype": "<class 'int'>", "value": 0, "label": "pixels"}, "solidity": {"trait": "solidity", "method": "plantcv.plantcv.analyze.size", "scale": "none", "datatype": "<class 'float'>", "value": 0, "label": "none"}, "perimeter": {"trait": "perimeter", "method": "plantcv.plantcv.analyze.size", "scale": "pixels", "datatype": "<class 'int'>", "value": 0, "label": "pixels"}, "width": {"trait": "width", "method": "plantcv.plantcv.analyze.size", "scale": "pixels", "datatype": "<class 'int'>", "value": 0, "label": "pixels"}, "height": {"trait": "height", "method": "plantcv.plantcv.analyze.size", "scale": "pixels", "datatype": "<class 'int'>", "value": 0, "label": "pixels"}, "longest_path": {"trait": "longest path", "method": "plantcv.plantcv.analyze.size", "scale": "pixels", "datatype": "<class 'int'>", "value": 0, "label": "pixels"}, "center_of_mass": {"trait": "center of mass", "method": "plantcv.plantcv.analyze.size", "scale": "none", "datatype": "<class 'tuple'>", "value": [0, 0], "label": ["x", "y"]}, "convex_hull_vertices": {"trait": "convex hull vertices", "method": "plantcv.plantcv.analyze.size", "scale": "none", "datatype": "<class 'int'>", "value": 0, "label": "none"}, "object_in_frame": {"trait": "object in frame", "method": "plantcv.plantcv.analyze.size", "scale": "none", "datatype": "<class 'bool'>", "value": true, "label": "none"}, "ellipse_center": {"trait": "ellipse center", "method": "plantcv.plantcv.analyze.size", "scale": "none", "datatype": "<class 'tuple'>", "value": [0, 0], "label": ["x", "y"]}, "ellipse_major_axis": {"trait": "ellipse major axis length", "method": "plantcv.plantcv.analyze.size", "scale": "pixels", "datatype": "<class 'int'>", "value": 0, "label": "pixels"}, "ellipse_minor_axis": {"trait": "ellipse minor axis length", "method": "plantcv.plantcv.analyze.size", "scale": "pixels", "datatype": "<class 'int'>", "value": 0, "label": "pixels"}, "ellipse_angle": {"trait": "ellipse major axis angle", "method": "plantcv.plantcv.analyze.size", "scale": "degrees", "datatype": "<class 'float'>", "value": 0.0, "label": "degrees"}, "ellipse_eccentricity": {"trait": "ellipse eccentricity", "method": "plantcv.plantcv.analyze.size", "scale": "none", "datatype": "<class 'float'>", "value": 0.0, "label": "none"}}, "plant_6": {"in_bounds": {"trait": "whether the plant goes out of bounds ", "method": "plantcv.plantcv.within_frame", "scale": "none", "datatype": "<class 'bool'>", "value": true, "label": "none"}, "area": {"trait": "area", "method": "plantcv.plantcv.analyze.size", "scale": "pixels", "datatype": "<class 'int'>", "value": 2330.0, "label": "pixels"}, "convex_hull_area": {"trait": "convex hull area", "method": "plantcv.plantcv.analyze.size", "scale": "pixels", "datatype": "<class 'int'>", "value": 33043.0, "label": "pixels"}, "solidity": {"trait": "solidity", "method": "plantcv.plantcv.analyze.size", "scale": "none", "datatype": "<class 'float'>", "value": 0.07051417849468875, "label": "none"}, "perimeter": {"trait": "perimeter", "method": "plantcv.plantcv.analyze.size", "scale": "pixels", "datatype": "<class 'int'>", "value": 1908.4388562440872, "label": "pixels"}, "width": {"trait": "width", "method": "plantcv.plantcv.analyze.size", "scale": "pixels", "datatype": "<class 'int'>", "value": 242, "label": "pixels"}, "height": {"trait": "height", "method": "plantcv.plantcv.analyze.size", "scale": "pixels", "datatype": "<class 'int'>", "value": 172, "label": "pixels"}, "longest_path": {"trait": "longest path", "method": "plantcv.plantcv.analyze.size", "scale": "pixels", "datatype": "<class 'int'>", "value": 1721, "label": "pixels"}, "center_of_mass": {"trait": "center of mass", "method": "plantcv.plantcv.analyze.size", "scale": "none", "datatype": "<class 'tuple'>", "value": [216.3008583690987, 219.28111587982832], "label": ["x", "y"]}, "convex_hull_vertices": {"trait": "convex hull vertices", "method": "plantcv.plantcv.analyze.size", "scale": "none", "datatype": "<class 'int'>", "value": 30, "label": "none"}, "object_in_frame": {"trait": "object in frame", "method": "plantcv.plantcv.analyze.size", "scale": "none", "datatype": "<class 'bool'>", "value": true, "label": "none"}, "ellipse_center": {"trait": "ellipse center", "method": "plantcv.plantcv.analyze.size", "scale": "none", "datatype": "<class 'tuple'>", "value": [153.61154174804688, 227.11572265625], "label": ["x", "y"]}, "ellipse_major_axis": {"trait": "ellipse major axis length", "method": "plantcv.plantcv.analyze.size", "scale": "pixels", "datatype": "<class 'int'>", "value": 235.39720153808594, "label": "pixels"}, "ellipse_minor_axis": {"trait": "ellipse minor axis length", "method": "plantcv.plantcv.analyze.size", "scale": "pixels", "datatype": "<class 'int'>", "value": 166.62393188476562, "label": "pixels"}, "ellipse_angle": {"trait": "ellipse major axis angle", "method": "plantcv.plantcv.analyze.size", "scale": "degrees", "datatype": "<class 'float'>", "value": 88.42952728271484, "label": "degrees"}, "ellipse_eccentricity": {"trait": "ellipse eccentricity", "method": "plantcv.plantcv.analyze.size", "scale": "none", "datatype": "<class 'float'>", "value": 0.7063711974823974, "label": "none"}}, "plant_7": {"in_bounds": {"trait": "whether the plant goes out of bounds ", "method": "plantcv.plantcv.within_frame", "scale": "none", "datatype": "<class 'bool'>", "value": true, "label": "none"}, "area": {"trait": "area", "method": "plantcv.plantcv.analyze.size", "scale": "pixels", "datatype": "<class 'int'>", "value": 1118.0, "label": "pixels"}, "convex_hull_area": {"trait": "convex hull area", "method": "plantcv.plantcv.analyze.size", "scale": "pixels", "datatype": "<class 'int'>", "value": 4497.5, "label": "pixels"}, "solidity": {"trait": "solidity", "method": "plantcv.plantcv.analyze.size", "scale": "none", "datatype": "<class 'float'>", "value": 0.24858254585881046, "label": "none"}, "perimeter": {"trait": "perimeter", "method": "plantcv.plantcv.analyze.size", "scale": "pixels", "datatype": "<class 'int'>", "value": 443.96758210659027, "label": "pixels"}, "width": {"trait": "width", "method": "plantcv.plantcv.analyze.size", "scale": "pixels", "datatype": "<class 'int'>", "value": 130, "label": "pixels"}, "height": {"trait": "height", "method": "plantcv.plantcv.analyze.size", "scale": "pixels", "datatype": "<class 'int'>", "value": 106, "label": "pixels"}, "longest_path": {"trait": "longest path", "method": "plantcv.plantcv.analyze.size", "scale": "pixels", "datatype": "<class 'int'>", "value": 1005, "label": "pixels"}, "center_of_mass": {"trait": "center of mass", "method": "plantcv.plantcv.analyze.size", "scale": "none", "datatype": "<class 'tuple'>", "value": [474.4096601073345, 230.8479427549195], "label": ["x", "y"]}, "convex_hull_vertices": {"trait": "convex hull vertices", "method": "plantcv.plantcv.analyze.size", "scale": "none", "datatype": "<class 'int'>", "value": 14, "label": "none"}, "object_in_frame": {"trait": "object in frame", "method": "plantcv.plantcv.analyze.size", "scale": "none", "datatype": "<class 'bool'>", "value": true, "label": "none"}, "ellipse_center": {"trait": "ellipse center", "method": "plantcv.plantcv.analyze.size", "scale": "none", "datatype": "<class 'tuple'>", "value": [436.0715026855469, 264.1109313964844], "label": ["x", "y"]}, "ellipse_major_axis": {"trait": "ellipse major axis length", "method": "plantcv.plantcv.analyze.size", "scale": "pixels", "datatype": "<class 'int'>", "value": 141.23023986816406, "label": "pixels"}, "ellipse_minor_axis": {"trait": "ellipse minor axis length", "method": "plantcv.plantcv.analyze.size", "scale": "pixels", "datatype": "<class 'int'>", "value": 62.43391799926758, "label": "pixels"}, "ellipse_angle": {"trait": "ellipse major axis angle", "method": "plantcv.plantcv.analyze.size", "scale": "degrees", "datatype": "<class 'float'>", "value": 49.300758361816406, "label": "degrees"}, "ellipse_eccentricity": {"trait": "ellipse eccentricity", "method": "plantcv.plantcv.analyze.size", "scale": "none", "datatype": "<class 'float'>", "value": 0.8969796267114006, "label": "none"}}, "plant_8": {"in_bounds": {"trait": "whether the plant goes out of bounds ", "method": "plantcv.plantcv.within_frame", "scale": "none", "datatype": "<class 'bool'>", "value": false, "label": "none"}, "area": {"trait": "area", "method": "plantcv.plantcv.analyze.size", "scale": "pixels", "datatype": "<class 'int'>", "value": 1231.0, "label": "pixels"}, "convex_hull_area": {"trait": "convex hull area", "method": "plantcv.plantcv.analyze.size", "scale": "pixels", "datatype": "<class 'int'>", "value": 34840.5, "label": "pixels"}, "solidity": {"trait": "solidity", "method": "plantcv.plantcv.analyze.size", "scale": "none", "datatype": "<class 'float'>", "value": 0.03533244356424276, "label": "none"}, "perimeter": {"trait": "perimeter", "method": "plantcv.plantcv.analyze.size", "scale": "pixels", "datatype": "<class 'int'>", "value": 1049.8676644563675, "label": "pixels"}, "width": {"trait": "width", "method": "plantcv.plantcv.analyze.size", "scale": "pixels", "datatype": "<class 'int'>", "value": 268, "label": "pixels"}, "height": {"trait": "height", "method": "plantcv.plantcv.analyze.size", "scale": "pixels", "datatype": "<class 'int'>", "value": 168, "label": "pixels"}, "longest_path": {"trait": "longest path", "method": "plantcv.plantcv.analyze.size", "scale": "pixels", "datatype": "<class 'int'>", "value": 1802, "label": "pixels"}, "center_of_mass": {"trait": "center of mass", "method": "plantcv.plantcv.analyze.size", "scale": "none", "datatype": "<class 'tuple'>", "value": [550.8034118602762, 206.12022745735175], "label": ["x", "y"]}, "convex_hull_vertices": {"trait": "convex hull vertices", "method": "plantcv.plantcv.analyze.size", "scale": "none", "datatype": "<class 'int'>", "value": 33, "label": "none"}, "object_in_frame": {"trait": "object in frame", "method": "plantcv.plantcv.analyze.size", "scale": "none", "datatype": "<class 'bool'>", "value": false, "label": "none"}, "ellipse_center": {"trait": "ellipse center", "method": "plantcv.plantcv.analyze.size", "scale": "none", "datatype": "<class 'tuple'>", "value": [485.8955078125, 209.96029663085938], "label": ["x", "y"]}, "ellipse_major_axis": {"trait": "ellipse major axis length", "method": "plantcv.plantcv.analyze.size", "scale": "pixels", "datatype": "<class 'int'>", "value": 282.15863037109375, "label": "pixels"}, "ellipse_minor_axis": {"trait": "ellipse minor axis length", "method": "plantcv.plantcv.analyze.size", "scale": "pixels", "datatype": "<class 'int'>", "value": 163.37014770507812, "label": "pixels"}, "ellipse_angle": {"trait": "ellipse major axis angle", "method": "plantcv.plantcv.analyze.size", "scale": "degrees", "datatype": "<class 'float'>", "value": 85.85930633544922, "label": "degrees"}, "ellipse_eccentricity": {"trait": "ellipse eccentricity", "method": "plantcv.plantcv.analyze.size", "scale": "none", "datatype": "<class 'float'>", "value": 0.8153267846825231, "label": "none"}}, "plant_9": {"in_bounds": {"trait": "whether the plant goes out of bounds ", "method": "plantcv.plantcv.within_frame", "scale": "none", "datatype": "<class 'bool'>", "value": true, "label": "none"}, "area": {"trait": "area", "method": "plantcv.plantcv.analyze.size", "scale": "pixels", "datatype": "<class 'int'>", "value": 0, "label": "pixels"}, "convex_hull_area": {"trait": "convex hull area", "method": "plantcv.plantcv.analyze.size", "scale": "pixels", "datatype": "<class 'int'>", "value": 0, "label": "pixels"}, "solidity": {"trait": "solidity", "method": "plantcv.plantcv.analyze.size", "scale": "none", "datatype": "<class 'float'>", "value": 0, "label": "none"}, "perimeter": {"trait": "perimeter", "method": "plantcv.plantcv.analyze.size", "scale": "pixels", "datatype": "<class 'int'>", "value": 0, "label": "pixels"}, "width": {"trait": "width", "method": "plantcv.plantcv.analyze.size", "scale": "pixels", "datatype": "<class 'int'>", "value": 0, "label": "pixels"}, "height": {"trait": "height", "method": "plantcv.plantcv.analyze.size", "scale": "pixels", "datatype": "<class 'int'>", "value": 0, "label": "pixels"}, "longest_path": {"trait": "longest path", "method": "plantcv.plantcv.analyze.size", "scale": "pixels", "datatype": "<class 'int'>", "value": 0, "label": "pixels"}, "center_of_mass": {"trait": "center of mass", "method": "plantcv.plantcv.analyze.size", "scale": "none", "datatype": "<class 'tuple'>", "value": [0, 0], "label": ["x", "y"]}, "convex_hull_vertices": {"trait": "convex hull vertices", "method": "plantcv.plantcv.analyze.size", "scale": "none", "datatype": "<class 'int'>", "value": 0, "label": "none"}, "object_in_frame": {"trait": "object in frame", "method": "plantcv.plantcv.analyze.size", "scale": "none", "datatype": "<class 'bool'>", "value": true, "label": "none"}, "ellipse_center": {"trait": "ellipse center", "method": "plantcv.plantcv.analyze.size", "scale": "none", "datatype": "<class 'tuple'>", "value": [0, 0], "label": ["x", "y"]}, "ellipse_major_axis": {"trait": "ellipse major axis length", "method": "plantcv.plantcv.analyze.size", "scale": "pixels", "datatype": "<class 'int'>", "value": 0, "label": "pixels"}, "ellipse_minor_axis": {"trait": "ellipse minor axis length", "method": "plantcv.plantcv.analyze.size", "scale": "pixels", "datatype": "<class 'int'>", "value": 0, "label": "pixels"}, "ellipse_angle": {"trait": "ellipse major axis angle", "method": "plantcv.plantcv.analyze.size", "scale": "degrees", "datatype": "<class 'float'>", "value": 0.0, "label": "degrees"}, "ellipse_eccentricity": {"trait": "ellipse eccentricity", "method": "plantcv.plantcv.analyze.size", "scale": "none", "datatype": "<class 'float'>", "value": 0.0, "label": "none"}}, "plant_10": {"in_bounds": {"trait": "whether the plant goes out of bounds ", "method": "plantcv.plantcv.within_frame", "scale": "none", "datatype": "<class 'bool'>", "value": true, "label": "none"}, "area": {"trait": "area", "method": "plantcv.plantcv.analyze.size", "scale": "pixels", "datatype": "<class 'int'>", "value": 1200.0, "label": "pixels"}, "convex_hull_area": {"trait": "convex hull area", "method": "plantcv.plantcv.analyze.size", "scale": "pixels", "datatype": "<class 'int'>", "value": 30079.0, "label": "pixels"}, "solidity": {"trait": "solidity", "method": "plantcv.plantcv.analyze.size", "scale": "none", "datatype": "<class 'float'>", "value": 0.039894943315934704, "label": "none"}, "perimeter": {"trait": "perimeter", "method": "plantcv.plantcv.analyze.size", "scale": "pixels", "datatype": "<class 'int'>", "value": 933.8461166620255, "label": "pixels"}, "width": {"trait": "width", "method": "plantcv.plantcv.analyze.size", "scale": "pixels", "datatype": "<class 'int'>", "value": 239, "label": "pixels"}, "height": {"trait": "height", "method": "plantcv.plantcv.analyze.size", "scale": "pixels", "datatype": "<class 'int'>", "value": 157, "label": "pixels"}, "longest_path": {"trait": "longest path", "method": "plantcv.plantcv.analyze.size", "scale": "pixels", "datatype": "<class 'int'>", "value": 1743, "label": "pixels"}, "center_of_mass": {"trait": "center of mass", "method": "plantcv.plantcv.analyze.size", "scale": "none", "datatype": "<class 'tuple'>", "value": [208.82333333333332, 368.8441666666667], "label": ["x", "y"]}, "convex_hull_vertices": {"trait": "convex hull vertices", "method": "plantcv.plantcv.analyze.size", "scale": "none", "datatype": "<class 'int'>", "value": 28, "label": "none"}, "object_in_frame": {"trait": "object in frame", "method": "plantcv.plantcv.analyze.size", "scale": "none", "datatype": "<class 'bool'>", "value": true, "label": "none"}, "ellipse_center": {"trait": "ellipse center", "method": "plantcv.plantcv.analyze.size", "scale": "none", "datatype": "<class 'tuple'>", "value": [152.72293090820312, 382.2496032714844], "label": ["x", "y"]}, "ellipse_major_axis": {"trait": "ellipse major axis length", "method": "plantcv.plantcv.analyze.size", "scale": "pixels", "datatype": "<class 'int'>", "value": 244.7873077392578, "label": "pixels"}, "ellipse_minor_axis": {"trait": "ellipse minor axis length", "method": "plantcv.plantcv.analyze.size", "scale": "pixels", "datatype": "<class 'int'>", "value": 160.05381774902344, "label": "pixels"}, "ellipse_angle": {"trait": "ellipse major axis angle", "method": "plantcv.plantcv.analyze.size", "scale": "degrees", "datatype": "<class 'float'>", "value": 83.16292572021484, "label": "degrees"}, "ellipse_eccentricity": {"trait": "ellipse eccentricity", "method": "plantcv.plantcv.analyze.size", "scale": "none", "datatype": "<class 'float'>", "value": 0.7566254812892644, "label": "none"}}, "plant_11": {"in_bounds": {"trait": "whether the plant goes out of bounds ", "method": "plantcv.plantcv.within_frame", "scale": "none", "datatype": "<class 'bool'>", "value": true, "label": "none"}, "area": {"trait": "area", "method": "plantcv.plantcv.analyze.size", "scale": "pixels", "datatype": "<class 'int'>", "value": 1969.0, "label": "pixels"}, "convex_hull_area": {"trait": "convex hull area", "method": "plantcv.plantcv.analyze.size", "scale": "pixels", "datatype": "<class 'int'>", "value": 68998.5, "label": "pixels"}, "solidity": {"trait": "solidity", "method": "plantcv.plantcv.analyze.size", "scale": "none", "datatype": "<class 'float'>", "value": 0.028536852250411242, "label": "none"}, "perimeter": {"trait": "perimeter", "method": "plantcv.plantcv.analyze.size", "scale": "pixels", "datatype": "<class 'int'>", "value": 1885.144604086876, "label": "pixels"}, "width": {"trait": "width", "method": "plantcv.plantcv.analyze.size", "scale": "pixels", "datatype": "<class 'int'>", "value": 281, "label": "pixels"}, "height": {"trait": "height", "method": "plantcv.plantcv.analyze.size", "scale": "pixels", "datatype": "<class 'int'>", "value": 322, "label": "pixels"}, "longest_path": {"trait": "longest path", "method": "plantcv.plantcv.analyze.size", "scale": "pixels", "datatype": "<class 'int'>", "value": 269, "label": "pixels"}, "center_of_mass": {"trait": "center of mass", "method": "plantcv.plantcv.analyze.size", "scale": "none", "datatype": "<class 'tuple'>", "value": [374.1376333164043, 332.8933468765871], "label": ["x", "y"]}, "convex_hull_vertices": {"trait": "convex hull vertices", "method": "plantcv.plantcv.analyze.size", "scale": "none", "datatype": "<class 'int'>", "value": 32, "label": "none"}, "object_in_frame": {"trait": "object in frame", "method": "plantcv.plantcv.analyze.size", "scale": "none", "datatype": "<class 'bool'>", "value": true, "label": "none"}, "ellipse_center": {"trait": "ellipse center", "method": "plantcv.plantcv.analyze.size", "scale": "none", "datatype": "<class 'tuple'>", "value": [329.43780517578125, 313.7401123046875], "label": ["x", "y"]}, "ellipse_major_axis": {"trait": "ellipse major axis length", "method": "plantcv.plantcv.analyze.size", "scale": "pixels", "datatype": "<class 'int'>", "value": 346.739013671875, "label": "pixels"}, "ellipse_minor_axis": {"trait": "ellipse minor axis length", "method": "plantcv.plantcv.analyze.size", "scale": "pixels", "datatype": "<class 'int'>", "value": 257.12841796875, "label": "pixels"}, "ellipse_angle": {"trait": "ellipse major axis angle", "method": "plantcv.plantcv.analyze.size", "scale": "degrees", "datatype": "<class 'float'>", "value": 163.6983642578125, "label": "degrees"}, "ellipse_eccentricity": {"trait": "ellipse eccentricity", "method": "plantcv.plantcv.analyze.size", "scale": "none", "datatype": "<class 'float'>", "value": 0.6708845283122219, "label": "none"}}, "plant_12": {"in_bounds": {"trait": "whether the plant goes out of bounds ", "method": "plantcv.plantcv.within_frame", "scale": "none", "datatype": "<class 'bool'>", "value": false, "label": "none"}, "area": {"trait": "area", "method": "plantcv.plantcv.analyze.size", "scale": "pixels", "datatype": "<class 'int'>", "value": 64699.0, "label": "pixels"}, "convex_hull_area": {"trait": "convex hull area", "method": "plantcv.plantcv.analyze.size", "scale": "pixels", "datatype": "<class 'int'>", "value": 310880.5, "label": "pixels"}, "solidity": {"trait": "solidity", "method": "plantcv.plantcv.analyze.size", "scale": "none", "datatype": "<class 'float'>", "value": 0.2081153369220649, "label": "none"}, "perimeter": {"trait": "perimeter", "method": "plantcv.plantcv.analyze.size", "scale": "pixels", "datatype": "<class 'int'>", "value": 5564.521274089813, "label": "pixels"}, "width": {"trait": "width", "method": "plantcv.plantcv.analyze.size", "scale": "pixels", "datatype": "<class 'int'>", "value": 650, "label": "pixels"}, "height": {"trait": "height", "method": "plantcv.plantcv.analyze.size", "scale": "pixels", "datatype": "<class 'int'>", "value": 489, "label": "pixels"}, "longest_path": {"trait": "longest path", "method": "plantcv.plantcv.analyze.size", "scale": "pixels", "datatype": "<class 'int'>", "value": 5003, "label": "pixels"}, "center_of_mass": {"trait": "center of mass", "method": "plantcv.plantcv.analyze.size", "scale": "none", "datatype": "<class 'tuple'>", "value": [219.9383916289278, 315.8625017388213], "label": ["x", "y"]}, "convex_hull_vertices": {"trait": "convex hull vertices", "method": "plantcv.plantcv.analyze.size", "scale": "none", "datatype": "<class 'int'>", "value": 5, "label": "none"}, "object_in_frame": {"trait": "object in frame", "method": "plantcv.plantcv.analyze.size", "scale": "none", "datatype": "<class 'bool'>", "value": false, "label": "none"}, "ellipse_center": {"trait": "ellipse center", "method": "plantcv.plantcv.analyze.size", "scale": "none", "datatype": "<class 'tuple'>", "value": [320.35931396484375, 273.10382080078125], "label": ["x", "y"]}, "ellipse_major_axis": {"trait": "ellipse major axis length", "method": "plantcv.plantcv.analyze.size", "scale": "pixels", "datatype": "<class 'int'>", "value": 667.2100219726562, "label": "pixels"}, "ellipse_minor_axis": {"trait": "ellipse minor axis length", "method": "plantcv.plantcv.analyze.size", "scale": "pixels", "datatype": "<class 'int'>", "value": 520.9159545898438, "label": "pixels"}, "ellipse_angle": {"trait": "ellipse major axis angle", "method": "plantcv.plantcv.analyze.size", "scale": "degrees", "datatype": "<class 'float'>", "value": 99.7269287109375, "label": "degrees"}, "ellipse_eccentricity": {"trait": "ellipse eccentricity", "method": "plantcv.plantcv.analyze.size", "scale": "none", "datatype": "<class 'float'>", "value": 0.6248590178048506, "label": "none"}}}}