{"metadata": {"image_height": {"datatype": "<class 'int'>", "value": [490]}, "image_width": {"datatype": "<class 'int'>", "value": [650]}, "run_date": {"datatype": "<class 'str'>", "value": ["2025-03-25T16:23:53.249762Z"]}, "plantcv_version": {"datatype": "<class 'str'>", "value": ["0.0.0"]}}, "observations": {"plant_1": {"in_bounds": {"trait": "whether the plant goes out of bounds ", "method": "plantcv.plantcv.within_frame", "scale": "none", "datatype": "<class 'bool'>", "value": true, "label": "none"}, "area": {"trait": "area", "method": "plantcv.plantcv.analyze.size", "scale": "pixels", "datatype": "<class 'int'>", "value": 1068.0, "label": "pixels"}, "convex_hull_area": {"trait": "convex hull area", "method": "plantcv.plantcv.analyze.size", "scale": "pixels", "datatype": "<class 'int'>", "value": 1533.0, "label": "pixels"}, "solidity": {"trait": "solidity", "method": "plantcv.plantcv.analyze.size", "scale": "none", "datatype": "<class 'float'>", "value": 0.6966731898238747, "label": "none"}, "perimeter": {"trait": "perimeter", "method": "plantcv.plantcv.analyze.size", "scale": "pixels", "datatype": "<class 'int'>", "value": 252.19618809223175, "label": "pixels"}, "width": {"trait": "width", "method": "plantcv.plantcv.analyze.size", "scale": "pixels", "datatype": "<class 'int'>", "value": 31, "label": "pixels"}, "height": {"trait": "height", "method": "plantcv.plantcv.analyze.size", "scale": "pixels", "datatype": "<class 'int'>", "value": 57, "label": "pixels"}, "longest_path": {"trait": "longest path", "method": "plantcv.plantcv.analyze.size", "scale": "pixels", "datatype": "<class 'int'>", "value": 398, "label": "pixels"}, "center_of_mass": {"trait": "center of mass", "method": "plantcv.plantcv.analyze.size", "scale": "none", "datatype": "<class 'tuple'>", "value": [81.6432584269663, 88.25468164794007], "label": ["x", "y"]}, "convex_hull_vertices": {"trait": "convex hull vertices", "method": "plantcv.plantcv.analyze.size", "scale": "none", "datatype": "<class 'int'>", "value": 17, "label": "none"}, "object_in_frame": {"trait": "object in frame", "method": "plantcv.plantcv.analyze.size", "scale": "none", "datatype": "<class 'bool'>", "value": true, "label": "none"}, "ellipse_center": {"trait": "ellipse center", "method": "plantcv.plantcv.analyze.size", "scale": "none", "datatype": "<class 'tuple'>", "value": [82.75123596191406, 87.80338287353516], "label": ["x", "y"]}, "ellipse_major_axis": {"trait": "ellipse major axis length", "method": "plantcv.plantcv.analyze.size", "scale": "pixels", "datatype": "<class 'int'>", "value": 60.83876419067383, "label": "pixels"}, "ellipse_minor_axis": {"trait": "ellipse minor axis length", "method": "plantcv.plantcv.analyze.size", "scale": "pixels", "datatype": "<class 'int'>", "value": 31.197364807128906, "label": "pixels"}, "ellipse_angle": {"trait": "ellipse major axis angle", "method": "plantcv.plantcv.analyze.size", "scale": "degrees", "datatype": "<class 'float'>", "value": 0.11896617710590363, "label": "degrees"}, "ellipse_eccentricity": {"trait": "ellipse eccentricity", "method": "plantcv.plantcv.analyze.size", "scale": "none", "datatype": "<class 'float'>", "value": 0.8585154987506262, "label": "none"}}, "plant_2": {"in_bounds": {"trait": "whether the plant goes out of bounds ", "method": "plantcv.plantcv.within_frame", "scale": "none", "datatype": "<class 'bool'>", "value": true, "label": "none"}, "area": {"trait": "area", "method": "plantcv.plantcv.analyze.size", "scale": "pixels", "datatype": "<class 'int'>", "value": 1469.0, "label": "pixels"}, "convex_hull_area": {"trait": "convex hull area", "method": "plantcv.plantcv.analyze.size", "scale": "pixels", "datatype": "<class 'int'>", "value": 2134.5, "label": "pixels"}, "solidity": {"trait": "solidity", "method": "plantcv.plantcv.analyze.size", "scale": "none", "datatype": "<class 'float'>", "value": 0.6882173811197002, "label": "none"}, "perimeter": {"trait": "perimeter", "method": "plantcv.plantcv.analyze.size", "scale": "pixels", "datatype": "<class 'int'>", "value": 302.4431508779526, "label": "pixels"}, "width": {"trait": "width", "method": "plantcv.plantcv.analyze.size", "scale": "pixels", "datatype": "<class 'int'>", "value": 42, "label": "pixels"}, "height": {"trait": "height", "method": "plantcv.plantcv.analyze.size", "scale": "pixels", "datatype": "<class 'int'>", "value": 64, "label": "pixels"}, "longest_path": {"trait": "longest path", "method": "plantcv.plantcv.analyze.size", "scale": "pixels", "datatype": "<class 'int'>", "value": 63, "label": "pixels"}, "center_of_mass": {"trait": "center of mass", "method": "plantcv.plantcv.analyze.size", "scale": "none", "datatype": "<class 'tuple'>", "value": [255.24574540503744, 112.33628318584071], "label": ["x", "y"]}, "convex_hull_vertices": {"trait": "convex hull vertices", "method": "plantcv.plantcv.analyze.size", "scale": "none", "datatype": "<class 'int'>", "value": 17, "label": "none"}, "object_in_frame": {"trait": "object in frame", "method": "plantcv.plantcv.analyze.size", "scale": "none", "datatype": "<class 'bool'>", "value": true, "label": "none"}, "ellipse_center": {"trait": "ellipse center", "method": "plantcv.plantcv.analyze.size", "scale": "none", "datatype": "<class 'tuple'>", "value": [254.98558044433594, 112.60897827148438], "label": ["x", "y"]}, "ellipse_major_axis": {"trait": "ellipse major axis length", "method": "plantcv.plantcv.analyze.size", "scale": "pixels", "datatype": "<class 'int'>", "value": 68.41181945800781, "label": "pixels"}, "ellipse_minor_axis": {"trait": "ellipse minor axis length", "method": "plantcv.plantcv.analyze.size", "scale": "pixels", "datatype": "<class 'int'>", "value": 38.21808624267578, "label": "pixels"}, "ellipse_angle": {"trait": "ellipse major axis angle", "method": "plantcv.plantcv.analyze.size", "scale": "degrees", "datatype": "<class 'float'>", "value": 6.300480842590332, "label": "degrees"}, "ellipse_eccentricity": {"trait": "ellipse eccentricity", "method": "plantcv.plantcv.analyze.size", "scale": "none", "datatype": "<class 'float'>", "value": 0.8294052467357657, "label": "none"}}, "plant_3": {"in_bounds": {"trait": "whether the plant goes out of bounds ", "method": "plantcv.plantcv.within_frame", "scale": "none", "datatype": "<class 'bool'>", "value": true, "label": "none"}, "area": {"trait": "area", "method": "plantcv.plantcv.analyze.size", "scale": "pixels", "datatype": "<class 'int'>", "value": 2768.0, "label": "pixels"}, "convex_hull_area": {"trait": "convex hull area", "method": "plantcv.plantcv.analyze.size", "scale": "pixels", "datatype": "<class 'int'>", "value": 4212.5, "label": "pixels"}, "solidity": {"trait": "solidity", "method": "plantcv.plantcv.analyze.size", "scale": "none", "datatype": "<class 'float'>", "value": 0.6570919881305638, "label": "none"}, "perimeter": {"trait": "perimeter", "method": "plantcv.plantcv.analyze.size", "scale": "pixels", "datatype": "<class 'int'>", "value": 374.7766922712326, "label": "pixels"}, "width": {"trait": "width", "method": "plantcv.plantcv.analyze.size", "scale": "pixels", "datatype": "<class 'int'>", "value": 68, "label": "pixels"}, "height": {"trait": "height", "method": "plantcv.plantcv.analyze.size", "scale": "pixels", "datatype": "<class 'int'>", "value": 86, "label": "pixels"}, "longest_path": {"trait": "longest path", "method": "plantcv.plantcv.analyze.size", "scale": "pixels", "datatype": "<class 'int'>", "value": 78, "label": "pixels"}, "center_of_mass": {"trait": "center of mass", "method": "plantcv.plantcv.analyze.size", "scale": "none", "datatype": "<class 'tuple'>", "value": [396.0509393063584, 83.72037572254335], "label": ["x", "y"]}, "convex_hull_vertices": {"trait": "convex hull vertices", "method": "plantcv.plantcv.analyze.size", "scale": "none", "datatype": "<class 'int'>", "value": 25, "label": "none"}, "object_in_frame": {"trait": "object in frame", "method": "plantcv.plantcv.analyze.size", "scale": "none", "datatype": "<class 'bool'>", "value": true, "label": "none"}, "ellipse_center": {"trait": "ellipse center", "method": "plantcv.plantcv.analyze.size", "scale": "none", "datatype": "<class 'tuple'>", "value": [392.95220947265625, 84.39725494384766], "label": ["x", "y"]}, "ellipse_major_axis": {"trait": "ellipse major axis length", "method": "plantcv.plantcv.analyze.size", "scale": "pixels", "datatype": "<class 'int'>", "value": 79.48414611816406, "label": "pixels"}, "ellipse_minor_axis": {"trait": "ellipse minor axis length", "method": "plantcv.plantcv.analyze.size", "scale": "pixels", "datatype": "<class 'int'>", "value": 62.35525894165039, "label": "pixels"}, "ellipse_angle": {"trait": "ellipse major axis angle", "method": "plantcv.plantcv.analyze.size", "scale": "degrees", "datatype": "<class 'float'>", "value": 173.39602661132812, "label": "degrees"}, "ellipse_eccentricity": {"trait": "ellipse eccentricity", "method": "plantcv.plantcv.analyze.size", "scale": "none", "datatype": "<class 'float'>", "value": 0.6201296717543231, "label": "none"}}, "plant_4": {"in_bounds": {"trait": "whether the plant goes out of bounds ", "method": "plantcv.plantcv.within_frame", "scale": "none", "datatype": "<class 'bool'>", "value": true, "label": "none"}, "area": {"trait": "area", "method": "plantcv.plantcv.analyze.size", "scale": "pixels", "datatype": "<class 'int'>", "value": 1447.0, "label": "pixels"}, "convex_hull_area": {"trait": "convex hull area", "method": "plantcv.plantcv.analyze.size", "scale": "pixels", "datatype": "<class 'int'>", "value": 2832.0, "label": "pixels"}, "solidity": {"trait": "solidity", "method": "plantcv.plantcv.analyze.size", "scale": "none", "datatype": "<class 'float'>", "value": 0.5109463276836158, "label": "none"}, "perimeter": {"trait": "perimeter", "method": "plantcv.plantcv.analyze.size", "scale": "pixels", "datatype": "<class 'int'>", "value": 396.0612634420395, "label": "pixels"}, "width": {"trait": "width", "method": "plantcv.plantcv.analyze.size", "scale": "pixels", "datatype": "<class 'int'>", "value": 56, "label": "pixels"}, "height": {"trait": "height", "method": "plantcv.plantcv.analyze.size", "scale": "pixels", "datatype": "<class 'int'>", "value": 76, "label": "pixels"}, "longest_path": {"trait": "longest path", "method": "plantcv.plantcv.analyze.size", "scale": "pixels", "datatype": "<class 'int'>", "value": 76, "label": "pixels"}, "center_of_mass": {"trait": "center of mass", "method": "plantcv.plantcv.analyze.size", "scale": "none", "datatype": "<class 'tuple'>", "value": [578.8548721492743, 88.56738078783691], "label": ["x", "y"]}, "convex_hull_vertices": {"trait": "convex hull vertices", "method": "plantcv.plantcv.analyze.size", "scale": "none", "datatype": "<class 'int'>", "value": 17, "label": "none"}, "object_in_frame": {"trait": "object in frame", "method": "plantcv.plantcv.analyze.size", "scale": "none", "datatype": "<class 'bool'>", "value": true, "label": "none"}, "ellipse_center": {"trait": "ellipse center", "method": "plantcv.plantcv.analyze.size", "scale": "none", "datatype": "<class 'tuple'>", "value": [579.791259765625, 87.96453094482422], "label": ["x", "y"]}, "ellipse_major_axis": {"trait": "ellipse major axis length", "method": "plantcv.plantcv.analyze.size", "scale": "pixels", "datatype": "<class 'int'>", "value": 72.71665954589844, "label": "pixels"}, "ellipse_minor_axis": {"trait": "ellipse minor axis length", "method": "plantcv.plantcv.analyze.size", "scale": "pixels", "datatype": "<class 'int'>", "value": 45.18293762207031, "label": "pixels"}, "ellipse_angle": {"trait": "ellipse major axis angle", "method": "plantcv.plantcv.analyze.size", "scale": "degrees", "datatype": "<class 'float'>", "value": 162.41018676757812, "label": "degrees"}, "ellipse_eccentricity": {"trait": "ellipse eccentricity", "method": "plantcv.plantcv.analyze.size", "scale": "none", "datatype": "<class 'float'>", "value": 0.783528325778519, "label": "none"}}, "plant_5": {"in_bounds": {"trait": "whether the plant goes out of bounds ", "method": "plantcv.plantcv.within_frame", "scale": "none", "datatype": "<class 'bool'>", "value": true, "label": "none"}, "area": {"trait": "area", "method": "plantcv.plantcv.analyze.size", "scale": "pixels", "datatype": "<class 'int'>", "value": 2872.0, "label": "pixels"}, "convex_hull_area": {"trait": "convex hull area", "method": "plantcv.plantcv.analyze.size", "scale": "pixels", "datatype": "<class 'int'>", "value": 4694.0, "label": "pixels"}, "solidity": {"trait": "solidity", "method": "plantcv.plantcv.analyze.size", "scale": "none", "datatype": "<class 'float'>", "value": 0.6118449083936941, "label": "none"}, "perimeter": {"trait": "perimeter", "method": "plantcv.plantcv.analyze.size", "scale": "pixels", "datatype": "<class 'int'>", "value": 510.279673576355, "label": "pixels"}, "width": {"trait": "width", "method": "plantcv.plantcv.analyze.size", "scale": "pixels", "datatype": "<class 'int'>", "value": 94, "label": "pixels"}, "height": {"trait": "height", "method": "plantcv.plantcv.analyze.size", "scale": "pixels", "datatype": "<class 'int'>", "value": 80, "label": "pixels"}, "longest_path": {"trait": "longest path", "method": "plantcv.plantcv.analyze.size", "scale": "pixels", "datatype": "<class 'int'>", "value": 688, "label": "pixels"}, "center_of_mass": {"trait": "center of mass", "method": "plantcv.plantcv.analyze.size", "scale": "none", "datatype": "<class 'tuple'>", "value": [72.42688022284122, 261.9808495821727], "label": ["x", "y"]}, "convex_hull_vertices": {"trait": "convex hull vertices", "method": "plantcv.plantcv.analyze.size", "scale": "none", "datatype": "<class 'int'>", "value": 21, "label": "none"}, "object_in_frame": {"trait": "object in frame", "method": "plantcv.plantcv.analyze.size", "scale": "none", "datatype": "<class 'bool'>", "value": true, "label": "none"}, "ellipse_center": {"trait": "ellipse center", "method": "plantcv.plantcv.analyze.size", "scale": "none", "datatype": "<class 'tuple'>", "value": [73.57914733886719, 256.17108154296875], "label": ["x", "y"]}, "ellipse_major_axis": {"trait": "ellipse major axis length", "method": "plantcv.plantcv.analyze.size", "scale": "pixels", "datatype": "<class 'int'>", "value": 91.08251953125, "label": "pixels"}, "ellipse_minor_axis": {"trait": "ellipse minor axis length", "method": "plantcv.plantcv.analyze.size", "scale": "pixels", "datatype": "<class 'int'>", "value": 64.0390625, "label": "pixels"}, "ellipse_angle": {"trait": "ellipse major axis angle", "method": "plantcv.plantcv.analyze.size", "scale": "degrees", "datatype": "<class 'float'>", "value": 126.53683471679688, "label": "degrees"}, "ellipse_eccentricity": {"trait": "ellipse eccentricity", "method": "plantcv.plantcv.analyze.size", "scale": "none", "datatype": "<class 'float'>", "value": 0.7111024598113935, "label": "none"}}, "plant_6": {"in_bounds": {"trait": "whether the plant goes out of bounds ", "method": "plantcv.plantcv.within_frame", "scale": "none", "datatype": "<class 'bool'>", "value": true, "label": "none"}, "area": {"trait": "area", "method": "plantcv.plantcv.analyze.size", "scale": "pixels", "datatype": "<class 'int'>", "value": 5197.0, "label": "pixels"}, "convex_hull_area": {"trait": "convex hull area", "method": "plantcv.plantcv.analyze.size", "scale": "pixels", "datatype": "<class 'int'>", "value": 17496.5, "label": "pixels"}, "solidity": {"trait": "solidity", "method": "plantcv.plantcv.analyze.size", "scale": "none", "datatype": "<class 'float'>", "value": 0.29703083473837627, "label": "none"}, "perimeter": {"trait": "perimeter", "method": "plantcv.plantcv.analyze.size", "scale": "pixels", "datatype": "<class 'int'>", "value": 1377.683585882187, "label": "pixels"}, "width": {"trait": "width", "method": "plantcv.plantcv.analyze.size", "scale": "pixels", "datatype": "<class 'int'>", "value": 165, "label": "pixels"}, "height": {"trait": "height", "method": "plantcv.plantcv.analyze.size", "scale": "pixels", "datatype": "<class 'int'>", "value": 114, "label": "pixels"}, "longest_path": {"trait": "longest path", "method": "plantcv.plantcv.analyze.size", "scale": "pixels", "datatype": "<class 'int'>", "value": 1295, "label": "pixels"}, "center_of_mass": {"trait": "center of mass", "method": "plantcv.plantcv.analyze.size", "scale": "none", "datatype": "<class 'tuple'>", "value": [218.62420627284973, 239.8593419280354], "label": ["x", "y"]}, "convex_hull_vertices": {"trait": "convex hull vertices", "method": "plantcv.plantcv.analyze.size", "scale": "none", "datatype": "<class 'int'>", "value": 21, "label": "none"}, "object_in_frame": {"trait": "object in frame", "method": "plantcv.plantcv.analyze.size", "scale": "none", "datatype": "<class 'bool'>", "value": true, "label": "none"}, "ellipse_center": {"trait": "ellipse center", "method": "plantcv.plantcv.analyze.size", "scale": "none", "datatype": "<class 'tuple'>", "value": [238.20252990722656, 231.5272674560547], "label": ["x", "y"]}, "ellipse_major_axis": {"trait": "ellipse major axis length", "method": "plantcv.plantcv.analyze.size", "scale": "pixels", "datatype": "<class 'int'>", "value": 179.07901000976562, "label": "pixels"}, "ellipse_minor_axis": {"trait": "ellipse minor axis length", "method": "plantcv.plantcv.analyze.size", "scale": "pixels", "datatype": "<class 'int'>", "value": 111.0932388305664, "label": "pixels"}, "ellipse_angle": {"trait": "ellipse major axis angle", "method": "plantcv.plantcv.analyze.size", "scale": "degrees", "datatype": "<class 'float'>", "value": 93.08577728271484, "label": "degrees"}, "ellipse_eccentricity": {"trait": "ellipse eccentricity", "method": "plantcv.plantcv.analyze.size", "scale": "none", "datatype": "<class 'float'>", "value": 0.784318153344847, "label": "none"}}, "plant_7": {"in_bounds": {"trait": "whether the plant goes out of bounds ", "method": "plantcv.plantcv.within_frame", "scale": "none", "datatype": "<class 'bool'>", "value": true, "label": "none"}, "area": {"trait": "area", "method": "plantcv.plantcv.analyze.size", "scale": "pixels", "datatype": "<class 'int'>", "value": 2870.0, "label": "pixels"}, "convex_hull_area": {"trait": "convex hull area", "method": "plantcv.plantcv.analyze.size", "scale": "pixels", "datatype": "<class 'int'>", "value": 4068.0, "label": "pixels"}, "solidity": {"trait": "solidity", "method": "plantcv.plantcv.analyze.size", "scale": "none", "datatype": "<class 'float'>", "value": 0.7055063913470994, "label": "none"}, "perimeter": {"trait": "perimeter", "method": "plantcv.plantcv.analyze.size", "scale": "pixels", "datatype": "<class 'int'>", "value": 414.20052230358124, "label": "pixels"}, "width": {"trait": "width", "method": "plantcv.plantcv.analyze.size", "scale": "pixels", "datatype": "<class 'int'>", "value": 57, "label": "pixels"}, "height": {"trait": "height", "method": "plantcv.plantcv.analyze.size", "scale": "pixels", "datatype": "<class 'int'>", "value": 87, "label": "pixels"}, "longest_path": {"trait": "longest path", "method": "plantcv.plantcv.analyze.size", "scale": "pixels", "datatype": "<class 'int'>", "value": 84, "label": "pixels"}, "center_of_mass": {"trait": "center of mass", "method": "plantcv.plantcv.analyze.size", "scale": "none", "datatype": "<class 'tuple'>", "value": [423.7425087108014, 261.9466898954704], "label": ["x", "y"]}, "convex_hull_vertices": {"trait": "convex hull vertices", "method": "plantcv.plantcv.analyze.size", "scale": "none", "datatype": "<class 'int'>", "value": 22, "label": "none"}, "object_in_frame": {"trait": "object in frame", "method": "plantcv.plantcv.analyze.size", "scale": "none", "datatype": "<class 'bool'>", "value": true, "label": "none"}, "ellipse_center": {"trait": "ellipse center", "method": "plantcv.plantcv.analyze.size", "scale": "none", "datatype": "<class 'tuple'>", "value": [421.62847900390625, 261.6937255859375], "label": ["x", "y"]}, "ellipse_major_axis": {"trait": "ellipse major axis length", "method": "plantcv.plantcv.analyze.size", "scale": "pixels", "datatype": "<class 'int'>", "value": 94.8722152709961, "label": "pixels"}, "ellipse_minor_axis": {"trait": "ellipse minor axis length", "method": "plantcv.plantcv.analyze.size", "scale": "pixels", "datatype": "<class 'int'>", "value": 52.671382904052734, "label": "pixels"}, "ellipse_angle": {"trait": "ellipse major axis angle", "method": "plantcv.plantcv.analyze.size", "scale": "degrees", "datatype": "<class 'float'>", "value": 171.85594177246094, "label": "degrees"}, "ellipse_eccentricity": {"trait": "ellipse eccentricity", "method": "plantcv.plantcv.analyze.size", "scale": "none", "datatype": "<class 'float'>", "value": 0.831728632137306, "label": "none"}}, "plant_8": {"in_bounds": {"trait": "whether the plant goes out of bounds ", "method": "plantcv.plantcv.within_frame", "scale": "none", "datatype": "<class 'bool'>", "value": true, "label": "none"}, "area": {"trait": "area", "method": "plantcv.plantcv.analyze.size", "scale": "pixels", "datatype": "<class 'int'>", "value": 1429.0, "label": "pixels"}, "convex_hull_area": {"trait": "convex hull area", "method": "plantcv.plantcv.analyze.size", "scale": "pixels", "datatype": "<class 'int'>", "value": 2460.5, "label": "pixels"}, "solidity": {"trait": "solidity", "method": "plantcv.plantcv.analyze.size", "scale": "none", "datatype": "<class 'float'>", "value": 0.5807762649867914, "label": "none"}, "perimeter": {"trait": "perimeter", "method": "plantcv.plantcv.analyze.size", "scale": "pixels", "datatype": "<class 'int'>", "value": 313.97361719608307, "label": "pixels"}, "width": {"trait": "width", "method": "plantcv.plantcv.analyze.size", "scale": "pixels", "datatype": "<class 'int'>", "value": 66, "label": "pixels"}, "height": {"trait": "height", "method": "plantcv.plantcv.analyze.size", "scale": "pixels", "datatype": "<class 'int'>", "value": 66, "label": "pixels"}, "longest_path": {"trait": "longest path", "method": "plantcv.plantcv.analyze.size", "scale": "pixels", "datatype": "<class 'int'>", "value": 506, "label": "pixels"}, "center_of_mass": {"trait": "center of mass", "method": "plantcv.plantcv.analyze.size", "scale": "none", "datatype": "<class 'tuple'>", "value": [572.8341497550734, 239.65500349895032], "label": ["x", "y"]}, "convex_hull_vertices": {"trait": "convex hull vertices", "method": "plantcv.plantcv.analyze.size", "scale": "none", "datatype": "<class 'int'>", "value": 18, "label": "none"}, "object_in_frame": {"trait": "object in frame", "method": "plantcv.plantcv.analyze.size", "scale": "none", "datatype": "<class 'bool'>", "value": true, "label": "none"}, "ellipse_center": {"trait": "ellipse center", "method": "plantcv.plantcv.analyze.size", "scale": "none", "datatype": "<class 'tuple'>", "value": [573.6602783203125, 240.1339874267578], "label": ["x", "y"]}, "ellipse_major_axis": {"trait": "ellipse major axis length", "method": "plantcv.plantcv.analyze.size", "scale": "pixels", "datatype": "<class 'int'>", "value": 71.39282989501953, "label": "pixels"}, "ellipse_minor_axis": {"trait": "ellipse minor axis length", "method": "plantcv.plantcv.analyze.size", "scale": "pixels", "datatype": "<class 'int'>", "value": 42.57780456542969, "label": "pixels"}, "ellipse_angle": {"trait": "ellipse major axis angle", "method": "plantcv.plantcv.analyze.size", "scale": "degrees", "datatype": "<class 'float'>", "value": 137.99046325683594, "label": "degrees"}, "ellipse_eccentricity": {"trait": "ellipse eccentricity", "method": "plantcv.plantcv.analyze.size", "scale": "none", "datatype": "<class 'float'>", "value": 0.8026965359756103, "label": "none"}}, "plant_9": {"in_bounds": {"trait": "whether the plant goes out of bounds ", "method": "plantcv.plantcv.within_frame", "scale": "none", "datatype": "<class 'bool'>", "value": false, "label": "none"}, "area": {"trait": "area", "method": "plantcv.plantcv.analyze.size", "scale": "pixels", "datatype": "<class 'int'>", "value": 943.0, "label": "pixels"}, "convex_hull_area": {"trait": "convex hull area", "method": "plantcv.plantcv.analyze.size", "scale": "pixels", "datatype": "<class 'int'>", "value": 4163.0, "label": "pixels"}, "solidity": {"trait": "solidity", "method": "plantcv.plantcv.analyze.size", "scale": "none", "datatype": "<class 'float'>", "value": 0.2265193370165746, "label": "none"}, "perimeter": {"trait": "perimeter", "method": "plantcv.plantcv.analyze.size", "scale": "pixels", "datatype": "<class 'int'>", "value": 423.58499932289124, "label": "pixels"}, "width": {"trait": "width", "method": "plantcv.plantcv.analyze.size", "scale": "pixels", "datatype": "<class 'int'>", "value": 73, "label": "pixels"}, "height": {"trait": "height", "method": "plantcv.plantcv.analyze.size", "scale": "pixels", "datatype": "<class 'int'>", "value": 98, "label": "pixels"}, "longest_path": {"trait": "longest path", "method": "plantcv.plantcv.analyze.size", "scale": "pixels", "datatype": "<class 'int'>", "value": 697, "label": "pixels"}, "center_of_mass": {"trait": "center of mass", "method": "plantcv.plantcv.analyze.size", "scale": "none", "datatype": "<class 'tuple'>", "value": [35.3796394485684, 365.46871686108165], "label": ["x", "y"]}, "convex_hull_vertices": {"trait": "convex hull vertices", "method": "plantcv.plantcv.analyze.size", "scale": "none", "datatype": "<class 'int'>", "value": 13, "label": "none"}, "object_in_frame": {"trait": "object in frame", "method": "plantcv.plantcv.analyze.size", "scale": "none", "datatype": "<class 'bool'>", "value": false, "label": "none"}, "ellipse_center": {"trait": "ellipse center", "method": "plantcv.plantcv.analyze.size", "scale": "none", "datatype": "<class 'tuple'>", "value": [37.82900619506836, 381.0359191894531], "label": ["x", "y"]}, "ellipse_major_axis": {"trait": "ellipse major axis length", "method": "plantcv.plantcv.analyze.size", "scale": "pixels", "datatype": "<class 'int'>", "value": 106.18788146972656, "label": "pixels"}, "ellipse_minor_axis": {"trait": "ellipse minor axis length", "method": "plantcv.plantcv.analyze.size", "scale": "pixels", "datatype": "<class 'int'>", "value": 85.47259521484375, "label": "pixels"}, "ellipse_angle": {"trait": "ellipse major axis angle", "method": "plantcv.plantcv.analyze.size", "scale": "degrees", "datatype": "<class 'float'>", "value": 113.17070770263672, "label": "degrees"}, "ellipse_eccentricity": {"trait": "ellipse eccentricity", "method": "plantcv.plantcv.analyze.size", "scale": "none", "datatype": "<class 'float'>", "value": 0.5933853161349356, "label": "none"}}, "plant_10": {"in_bounds": {"trait": "whether the plant goes out of bounds ", "method": "plantcv.plantcv.within_frame", "scale": "none", "datatype": "<class 'bool'>", "value": true, "label": "none"}, "area": {"trait": "area", "method": "plantcv.plantcv.analyze.size", "scale": "pixels", "datatype": "<class 'int'>", "value": 3525.0, "label": "pixels"}, "convex_hull_area": {"trait": "convex hull area", "method": "plantcv.plantcv.analyze.size", "scale": "pixels", "datatype": "<class 'int'>", "value": 12380.5, "label": "pixels"}, "solidity": {"trait": "solidity", "method": "plantcv.plantcv.analyze.size", "scale": "none", "datatype": "<class 'float'>", "value": 0.2847219417632567, "label": "none"}, "perimeter": {"trait": "perimeter", "method": "plantcv.plantcv.analyze.size", "scale": "pixels", "datatype": "<class 'int'>", "value": 1059.8050819635391, "label": "pixels"}, "width": {"trait": "width", "method": "plantcv.plantcv.analyze.size", "scale": "pixels", "datatype": "<class 'int'>", "value": 143, "label": "pixels"}, "height": {"trait": "height", "method": "plantcv.plantcv.analyze.size", "scale": "pixels", "datatype": "<class 'int'>", "value": 188, "label": "pixels"}, "longest_path": {"trait": "longest path", "method": "plantcv.plantcv.analyze.size", "scale": "pixels", "datatype": "<class 'int'>", "value": 1460, "label": "pixels"}, "center_of_mass": {"trait": "center of mass", "method": "plantcv.plantcv.analyze.size", "scale": "none", "datatype": "<class 'tuple'>", "value": [246.9977304964539, 409.3375886524823], "label": ["x", "y"]}, "convex_hull_vertices": {"trait": "convex hull vertices", "method": "plantcv.plantcv.analyze.size", "scale": "none", "datatype": "<class 'int'>", "value": 24, "label": "none"}, "object_in_frame": {"trait": "object in frame", "method": "plantcv.plantcv.analyze.size", "scale": "none", "datatype": "<class 'bool'>", "value": true, "label": "none"}, "ellipse_center": {"trait": "ellipse center", "method": "plantcv.plantcv.analyze.size", "scale": "none", "datatype": "<class 'tuple'>", "value": [219.4399871826172, 389.0638122558594], "label": ["x", "y"]}, "ellipse_major_axis": {"trait": "ellipse major axis length", "method": "plantcv.plantcv.analyze.size", "scale": "pixels", "datatype": "<class 'int'>", "value": 186.6282501220703, "label": "pixels"}, "ellipse_minor_axis": {"trait": "ellipse minor axis length", "method": "plantcv.plantcv.analyze.size", "scale": "pixels", "datatype": "<class 'int'>", "value": 83.65560150146484, "label": "pixels"}, "ellipse_angle": {"trait": "ellipse major axis angle", "method": "plantcv.plantcv.analyze.size", "scale": "degrees", "datatype": "<class 'float'>", "value": 142.2624969482422, "label": "degrees"}, "ellipse_eccentricity": {"trait": "ellipse eccentricity", "method": "plantcv.plantcv.analyze.size", "scale": "none", "datatype": "<class 'float'>", "value": 0.8939096123905858, "label": "none"}}, "plant_11": {"in_bounds": {"trait": "whether the plant goes out of bounds ", "method": "plantcv.plantcv.within_frame", "scale": "none", "datatype": "<class 'bool'>", "value": true, "label": "none"}, "area": {"trait": "area", "method": "plantcv.plantcv.analyze.size", "scale": "pixels", "datatype": "<class 'int'>", "value": 2327.0, "label": "pixels"}, "convex_hull_area": {"trait": "convex hull area", "method": "plantcv.plantcv.analyze.size", "scale": "pixels", "datatype": "<class 'int'>", "value": 6414.0, "label": "pixels"}, "solidity": {"trait": "solidity", "method": "plantcv.plantcv.analyze.size", "scale": "none", "datatype": "<class 'float'>", "value": 0.36280012472715933, "label": "none"}, "perimeter": {"trait": "perimeter", "method": "plantcv.plantcv.analyze.size", "scale": "pixels", "datatype": "<class 'int'>", "value": 702.2212557792664, "label": "pixels"}, "width": {"trait": "width", "method": "plantcv.plantcv.analyze.size", "scale": "pixels", "datatype": "<class 'int'>", "value": 99, "label": "pixels"}, "height": {"trait": "height", "method": "plantcv.plantcv.analyze.size", "scale": "pixels", "datatype": "<class 'int'>", "value": 137, "label": "pixels"}, "longest_path": {"trait": "longest path", "method": "plantcv.plantcv.analyze.size", "scale": "pixels", "datatype": "<class 'int'>", "value": 1088, "label": "pixels"}, "center_of_mass": {"trait": "center of mass", "method": "plantcv.plantcv.analyze.size", "scale": "none", "datatype": "<class 'tuple'>", "value": [391.50752041254833, 408.1216158143532], "label": ["x", "y"]}, "convex_hull_vertices": {"trait": "convex hull vertices", "method": "plantcv.plantcv.analyze.size", "scale": "none", "datatype": "<class 'int'>", "value": 14, "label": "none"}, "object_in_frame": {"trait": "object in frame", "method": "plantcv.plantcv.analyze.size", "scale": "none", "datatype": "<class 'bool'>", "value": true, "label": "none"}, "ellipse_center": {"trait": "ellipse center", "method": "plantcv.plantcv.analyze.size", "scale": "none", "datatype": "<class 'tuple'>", "value": [405.1853332519531, 384.6545104980469], "label": ["x", "y"]}, "ellipse_major_axis": {"trait": "ellipse major axis length", "method": "plantcv.plantcv.analyze.size", "scale": "pixels", "datatype": "<class 'int'>", "value": 151.019287109375, "label": "pixels"}, "ellipse_minor_axis": {"trait": "ellipse minor axis length", "method": "plantcv.plantcv.analyze.size", "scale": "pixels", "datatype": "<class 'int'>", "value": 48.48127746582031, "label": "pixels"}, "ellipse_angle": {"trait": "ellipse major axis angle", "method": "plantcv.plantcv.analyze.size", "scale": "degrees", "datatype": "<class 'float'>", "value": 26.926185607910156, "label": "degrees"}, "ellipse_eccentricity": {"trait": "ellipse eccentricity", "method": "plantcv.plantcv.analyze.size", "scale": "none", "datatype": "<class 'float'>", "value": 0.9470700227177018, "label": "none"}}, "plant_12": {"in_bounds": {"trait": "whether the plant goes out of bounds ", "method": "plantcv.plantcv.within_frame", "scale": "none", "datatype": "<class 'bool'>", "value": true, "label": "none"}, "area": {"trait": "area", "method": "plantcv.plantcv.analyze.size", "scale": "pixels", "datatype": "<class 'int'>", "value": 1311.0, "label": "pixels"}, "convex_hull_area": {"trait": "convex hull area", "method": "plantcv.plantcv.analyze.size", "scale": "pixels", "datatype": "<class 'int'>", "value": 3194.0, "label": "pixels"}, "solidity": {"trait": "solidity", "method": "plantcv.plantcv.analyze.size", "scale": "none", "datatype": "<class 'float'>", "value": 0.41045710707576705, "label": "none"}, "perimeter": {"trait": "perimeter", "method": "plantcv.plantcv.analyze.size", "scale": "pixels", "datatype": "<class 'int'>", "value": 432.62564516067505, "label": "pixels"}, "width": {"trait": "width", "method": "plantcv.plantcv.analyze.size", "scale": "pixels", "datatype": "<class 'int'>", "value": 74, "label": "pixels"}, "height": {"trait": "height", "method": "plantcv.plantcv.analyze.size", "scale": "pixels", "datatype": "<class 'int'>", "value": 66, "label": "pixels"}, "longest_path": {"trait": "longest path", "method": "plantcv.plantcv.analyze.size", "scale": "pixels", "datatype": "<class 'int'>", "value": 503, "label": "pixels"}, "center_of_mass": {"trait": "center of mass", "method": "plantcv.plantcv.analyze.size", "scale": "none", "datatype": "<class 'tuple'>", "value": [582.881769641495, 408.1990846681922], "label": ["x", "y"]}, "convex_hull_vertices": {"trait": "convex hull vertices", "method": "plantcv.plantcv.analyze.size", "scale": "none", "datatype": "<class 'int'>", "value": 17, "label": "none"}, "object_in_frame": {"trait": "object in frame", "method": "plantcv.plantcv.analyze.size", "scale": "none", "datatype": "<class 'bool'>", "value": true, "label": "none"}, "ellipse_center": {"trait": "ellipse center", "method": "plantcv.plantcv.analyze.size", "scale": "none", "datatype": "<class 'tuple'>", "value": [578.527099609375, 403.5804748535156], "label": ["x", "y"]}, "ellipse_major_axis": {"trait": "ellipse major axis length", "method": "plantcv.plantcv.analyze.size", "scale": "pixels", "datatype": "<class 'int'>", "value": 67.42131042480469, "label": "pixels"}, "ellipse_minor_axis": {"trait": "ellipse minor axis length", "method": "plantcv.plantcv.analyze.size", "scale": "pixels", "datatype": "<class 'int'>", "value": 59.36455535888672, "label": "pixels"}, "ellipse_angle": {"trait": "ellipse major axis angle", "method": "plantcv.plantcv.analyze.size", "scale": "degrees", "datatype": "<class 'float'>", "value": 66.35714721679688, "label": "degrees"}, "ellipse_eccentricity": {"trait": "ellipse eccentricity", "method": "plantcv.plantcv.analyze.size", "scale": "none", "datatype": "<class 'float'>", "value": 0.474043625945082, "label": "none"}}}}